Workbook

Sheet README
A1: Epic 5 — Prioritization Model | E-Commerce CRO Analytics
A2: PROJECT-READY • Formula QA • Synthetic data • INDEX/MATCH compatible
A3: Purpose | B3: Excel model for Q3 cart-abandonment root-cause prioritization, using ICE scoring plus an AOV × conversion-lift what-if calculator.
A4: Source basis | B4: Ireland_prep.docx defines Epic 5 as: build ICE/PIE scoring with live formulas; build an AOV × conversion-lift what-if using XLOOKUP/INDEX-MATCH; rank the backlog. This workbook uses INDEX/MATCH for broader Excel compatibility.
A5: Synthetic-data policy | B5: All project data is synthetic. No real client data, screenshots, brand names, or live GA4 exports are used.
A6: Orders source logic | B6: Cart_abdn.py defines abandonment as sessions whose exit_page is Cart or Checkout. The supplied Sessions_table.py generates 1,800 sessions, producing 322 Cart/Checkout abandonment sessions; the workbook now uses that generated count.
A7: Abandonment source logic | B7: 1) Review source-backed inputs. 2) Review generated abandonment counts and reason shares. 3) Adjust only the blue recoverability / ICE hypothesis cells. 4) Use What_If for scenario testing.
A8: Important limitation | B8: The supplied Sessions_table.py generates 1,800 sessions; Cart_abdn.py defines abandonment as sessions exiting at Cart or Checkout. With the supplied seed and logic, this yields 322 abandonment sessions. Revenue remains a planning estimate based on the supplied AOV-generation parameters.
A9: How to use | B9: 1) Edit blue input cells on Inputs. 2) Review reason shares on Abandonment. 3) Adjust fix assumptions and inspect ICE_Backlog. 4) Use What_If for scenario testing.
A10: Generated session check | B10: 1,800 sessions generated; 322 exit at Cart/Checkout under the supplied Sessions_table.py seed/logic and feed Cart_abdn.py.

Sheet Inputs
A1: Model Inputs
A3: Input | B3: Value | C3: Unit | D3: Source / rationale | E3: Editable?
A4: Total orders | B4: 850 | C4: orders | D4: Orders_table.py: total_orders = 850 | E4: No
A5: Completion rate | B5: 0.92 | C5: % | D5: Orders_table.py: 92% complete | E5: No
A6: Discount usage rate | B6: 0.3 | C6: % | D6: Orders_table.py: 30% discount usage | E6: No
A7: Lognormal AOV mean parameter | B7: 4 | C7: ln(AOV) | D7: Orders_table.py: mean=4.0 | E7: No
A8: Lognormal AOV sigma | B8: 0.6 | C8: ln(AOV) | D8: Orders_table.py: sigma=0.6 | E8: No
A9: Generated cart/checkout abandonment sessions | B9: 322 | C9: sessions | D9: Sessions_table.py: 1,800 sessions; Cart_abdn.py uses Cart + Checkout exits. | E9: No
A10: Base conversion rate | B10: =IF(B4=0,0,(B4*B5)/B4) -> 0.92 | C10: % | D10: Completed orders ÷ total orders; formula | E10: No
A11: Theoretical mean AOV | B11: =EXP(B7+(B8^2)/2) -> 65.365853 | C11: € | D11: Derived from supplied lognormal parameters; formula | E11: No
A12: Theoretical median AOV | B12: =EXP(B7) -> 54.59815 | C12: € | D12: Derived from supplied lognormal parameters; formula | E12: No
A14: Data note | B14: The supplied Sessions_table.py generates 1,800 sessions. Cart_abdn.py defines abandonment as sessions exiting at Cart or Checkout. The generated source logic produces 322 such sessions.

Sheet Abandonment
A1: Abandonment Reason Model
A3: Reason | B3: Source Weight | C3: Planning Sessions | D3: Estimated Lost Revenue Proxy | E3: Recoverability Assumption | F3: Recoverable Revenue Proxy | G3: Share of Lost Revenue | H3: Source | I3: Generated Count
A4: Size/fit doubt | B4: =IF($C$10=0,0,C4/$C$10) -> 0.45341615 | C4: =I4 -> 146 | D4: =C4*Inputs!$B$11 -> 9543.4146 | E4: 0.25 | F4: =D4*E4 -> 2385.8536 | G4: =IF(SUM($D$4:$D$9)=0,0,D4/SUM($D$4:$D$9)) -> 0.45341615 | H4: Cart_abdn.py weighted draw | I4: 146
A5: Shipping cost too high | B5: =IF($C$10=0,0,C5/$C$10) -> 0.23913043 | C5: =I5 -> 77 | D5: =C5*Inputs!$B$11 -> 5033.1707 | E5: 0.2 | F5: =D5*E5 -> 1006.6341 | G5: =IF(SUM($D$4:$D$9)=0,0,D5/SUM($D$4:$D$9)) -> 0.23913043 | H5: Cart_abdn.py weighted draw | I5: 77
A6: Just browsing/saved for later | B6: =IF($C$10=0,0,C6/$C$10) -> 0.14906832 | C6: =I6 -> 48 | D6: =C6*Inputs!$B$11 -> 3137.561 | E6: 0.08 | F6: =D6*E6 -> 251.00488 | G6: =IF(SUM($D$4:$D$9)=0,0,D6/SUM($D$4:$D$9)) -> 0.14906832 | H6: Cart_abdn.py weighted draw | I6: 48
A7: Found better price elsewhere | B7: =IF($C$10=0,0,C7/$C$10) -> 0.071428571 | C7: =I7 -> 23 | D7: =C7*Inputs!$B$11 -> 1503.4146 | E7: 0.12 | F7: =D7*E7 -> 180.40975 | G7: =IF(SUM($D$4:$D$9)=0,0,D7/SUM($D$4:$D$9)) -> 0.071428571 | H7: Cart_abdn.py weighted draw | I7: 23
A8: Payment method declined | B8: =IF($C$10=0,0,C8/$C$10) -> 0.052795031 | C8: =I8 -> 17 | D8: =C8*Inputs!$B$11 -> 1111.2195 | E8: 0.35 | F8: =D8*E8 -> 388.92683 | G8: =IF(SUM($D$4:$D$9)=0,0,D8/SUM($D$4:$D$9)) -> 0.052795031 | H8: Cart_abdn.py weighted draw | I8: 17
A9: Website technical error | B9: =IF($C$10=0,0,C9/$C$10) -> 0.034161491 | C9: =I9 -> 11 | D9: =C9*Inputs!$B$11 -> 719.02439 | E9: 0.5 | F9: =D9*E9 -> 359.51219 | G9: =IF(SUM($D$4:$D$9)=0,0,D9/SUM($D$4:$D$9)) -> 0.034161491 | H9: Cart_abdn.py weighted draw | I9: 11
A10: Total / weighted view | C10: =SUM(C4:C9) -> 322 | D10: =SUM(D4:D9) -> 21047.805 | F10: =SUM(F4:F9) -> 4572.3414 | G10: =SUM(G4:G9) -> 1
A12: Data note | B12: Planning revenue proxy = abandonment sessions × theoretical mean AOV from the supplied lognormal generation parameters; recoverability is an analyst hypothesis, not observed revenue. | D12: Planning revenue proxy = abandonment sessions × theoretical mean AOV from the supplied lognormal generation parameters; recoverability is an analyst hypothesis, not observed revenue.

Sheet ICE_Backlog
A1: ICE Prioritization Backlog
A3: Fix ID | B3: Proposed Fix | C3: Reason | D3: Impact Score (1–10) | E3: Confidence (1–10) | F3: Ease (1–10) | G3: ICE Score | H3: Rank | I3: Reason Share | J3: Recoverable Revenue | K3: Projected Monthly Revenue | L3: Status | M3: Rationale
A4: FIX-01 | B4: Add fit guide + size recommendation | C4: Size/fit doubt | D4: 8 | E4: 7 | F4: 7 | G4: =D4*E4*F4/1000 -> 0.392 | H4: =RANK(G4,$G$4:$G$9,0) -> 1 | I4: =IFERROR(INDEX(Abandonment!$B$4:$B$9,MATCH(C4,Abandonment!$A$4:$A$9,0)),0) -> 0.45341615 | J4: =IFERROR(INDEX(Abandonment!$F$4:$F$9,MATCH(C4,Abandonment!$A$4:$A$9,0)),0) -> 2385.8536 | K4: =J4 -> 2385.8536 | L4: In discovery | M4: Score assumptions are analyst hypotheses for portfolio prioritization; revise as evidence becomes available.
A5: FIX-02 | B5: Show shipping cost/threshold earlier | C5: Shipping cost too high | D5: 8 | E5: 8 | F5: 6 | G5: =D5*E5*F5/1000 -> 0.384 | H5: =RANK(G5,$G$4:$G$9,0) -> 2 | I5: =IFERROR(INDEX(Abandonment!$B$4:$B$9,MATCH(C5,Abandonment!$A$4:$A$9,0)),0) -> 0.23913043 | J5: =IFERROR(INDEX(Abandonment!$F$4:$F$9,MATCH(C5,Abandonment!$A$4:$A$9,0)),0) -> 1006.6341 | K5: =J5 -> 1006.6341 | L5: In discovery | M5: Score assumptions are analyst hypotheses for portfolio prioritization; revise as evidence becomes available.
A6: FIX-03 | B6: Add payment-method fallback + clearer errors | C6: Payment method declined | D6: 6 | E6: 8 | F6: 7 | G6: =D6*E6*F6/1000 -> 0.336 | H6: =RANK(G6,$G$4:$G$9,0) -> 3 | I6: =IFERROR(INDEX(Abandonment!$B$4:$B$9,MATCH(C6,Abandonment!$A$4:$A$9,0)),0) -> 0.052795031 | J6: =IFERROR(INDEX(Abandonment!$F$4:$F$9,MATCH(C6,Abandonment!$A$4:$A$9,0)),0) -> 388.92683 | K6: =J6 -> 388.92683 | L6: In discovery | M6: Score assumptions are analyst hypotheses for portfolio prioritization; revise as evidence becomes available.
A7: FIX-04 | B7: Strengthen price/value messaging | C7: Found better price elsewhere | D7: 5 | E7: 6 | F7: 7 | G7: =D7*E7*F7/1000 -> 0.21 | H7: =RANK(G7,$G$4:$G$9,0) -> 5 | I7: =IFERROR(INDEX(Abandonment!$B$4:$B$9,MATCH(C7,Abandonment!$A$4:$A$9,0)),0) -> 0.071428571 | J7: =IFERROR(INDEX(Abandonment!$F$4:$F$9,MATCH(C7,Abandonment!$A$4:$A$9,0)),0) -> 180.40975 | K7: =J7 -> 180.40975 | L7: In discovery | M7: Score assumptions are analyst hypotheses for portfolio prioritization; revise as evidence becomes available.
A8: FIX-05 | B8: Improve technical error recovery + retry | C8: Website technical error | D8: 7 | E8: 7 | F8: 5 | G8: =D8*E8*F8/1000 -> 0.245 | H8: =RANK(G8,$G$4:$G$9,0) -> 4 | I8: =IFERROR(INDEX(Abandonment!$B$4:$B$9,MATCH(C8,Abandonment!$A$4:$A$9,0)),0) -> 0.034161491 | J8: =IFERROR(INDEX(Abandonment!$F$4:$F$9,MATCH(C8,Abandonment!$A$4:$A$9,0)),0) -> 359.51219 | K8: =J8 -> 359.51219 | L8: In discovery | M8: Score assumptions are analyst hypotheses for portfolio prioritization; revise as evidence becomes available.
A9: FIX-06 | B9: Add save-for-later / wishlist prompt | C9: Just browsing/saved for later | D9: 4 | E9: 5 | F9: 8 | G9: =D9*E9*F9/1000 -> 0.16 | H9: =RANK(G9,$G$4:$G$9,0) -> 6 | I9: =IFERROR(INDEX(Abandonment!$B$4:$B$9,MATCH(C9,Abandonment!$A$4:$A$9,0)),0) -> 0.14906832 | J9: =IFERROR(INDEX(Abandonment!$F$4:$F$9,MATCH(C9,Abandonment!$A$4:$A$9,0)),0) -> 251.00488 | K9: =J9 -> 251.00488 | L9: In discovery | M9: Score assumptions are analyst hypotheses for portfolio prioritization; revise as evidence becomes available.
A11: Formula note | B11: ICE Score = Impact × Confidence × Ease / 1000. Impact is a 1–10 hypothesis score; revenue is separately formula-derived from the abandonment model. | M11: ICE Score = Impact × Confidence × Ease / 1000. Lookup fields use INDEX/MATCH for compatibility. Impact is a 1–10 hypothesis score; revenue is formula-derived from the abandonment model.

Sheet What_If
A1: AOV × Conversion-Lift What-If Calculator
A3: Scenario | B3: AOV (€) | C3: Conversion Lift | D3: Selected AOV | E3: Selected Lift | F3: Base Completed Orders | G3: Incremental Orders | H3: Incremental Revenue | I3: Annualized Revenue | J3: Formula
A4: Conservative | B4: 55 | C4: 0.02 | D4: =IFERROR(INDEX($B$4:$B$6,MATCH($B$9,$A$4:$A$6,0)),0) -> 65.5 | E4: =IFERROR(INDEX($C$4:$C$6,MATCH($B$9,$A$4:$A$6,0)),0) -> 0.05 | F4: =Inputs!$B$4*Inputs!$B$5 -> 782 | G4: =F4*E4 -> 39.1 | H4: =G4*D4 -> 2561.05 | I4: =H4 -> 2561.05 | J4: Incremental orders = base completed orders × lift; revenue = incremental orders × selected AOV.
A5: Base | B5: 65.5 | C5: 0.05
A6: Upside | B6: 80 | C6: 0.08
A9: Selected scenario | B9: Base
A11: How this supports Epic 5 | B11: Use the selector to test the revenue effect of a hypothetical conversion lift at different AOV levels. Scenario values are planning assumptions and should be replaced with evidence where available.
A14: Fix ID | B14: Fix | C14: Reason | D14: ICE Score | E14: Recoverable Revenue | F14: INDEX/MATCH source
A15: =ICE_Backlog!A4 -> FIX-01 | B15: =ICE_Backlog!B4 -> Add fit guide + size recommendation | C15: =ICE_Backlog!C4 -> Size/fit doubt | D15: =IFERROR(INDEX(ICE_Backlog!$G$4:$G$9,MATCH(A15,ICE_Backlog!$A$4:$A$9,0)),0) -> 0.392 | E15: =IFERROR(INDEX(ICE_Backlog!$J$4:$J$9,MATCH(A15,ICE_Backlog!$A$4:$A$9,0)),0) -> 2385.8536 | F15: ICE_Backlog
A16: =ICE_Backlog!A5 -> FIX-02 | B16: =ICE_Backlog!B5 -> Show shipping cost/threshold earlier | C16: =ICE_Backlog!C5 -> Shipping cost too high | D16: =IFERROR(INDEX(ICE_Backlog!$G$4:$G$9,MATCH(A16,ICE_Backlog!$A$4:$A$9,0)),0) -> 0.384 | E16: =IFERROR(INDEX(ICE_Backlog!$J$4:$J$9,MATCH(A16,ICE_Backlog!$A$4:$A$9,0)),0) -> 1006.6341 | F16: ICE_Backlog
A17: =ICE_Backlog!A6 -> FIX-03 | B17: =ICE_Backlog!B6 -> Add payment-method fallback + clearer errors | C17: =ICE_Backlog!C6 -> Payment method declined | D17: =IFERROR(INDEX(ICE_Backlog!$G$4:$G$9,MATCH(A17,ICE_Backlog!$A$4:$A$9,0)),0) -> 0.336 | E17: =IFERROR(INDEX(ICE_Backlog!$J$4:$J$9,MATCH(A17,ICE_Backlog!$A$4:$A$9,0)),0) -> 388.92683 | F17: ICE_Backlog
A18: =ICE_Backlog!A7 -> FIX-04 | B18: =ICE_Backlog!B7 -> Strengthen price/value messaging | C18: =ICE_Backlog!C7 -> Found better price elsewhere | D18: =IFERROR(INDEX(ICE_Backlog!$G$4:$G$9,MATCH(A18,ICE_Backlog!$A$4:$A$9,0)),0) -> 0.21 | E18: =IFERROR(INDEX(ICE_Backlog!$J$4:$J$9,MATCH(A18,ICE_Backlog!$A$4:$A$9,0)),0) -> 180.40975 | F18: ICE_Backlog
A19: =ICE_Backlog!A8 -> FIX-05 | B19: =ICE_Backlog!B8 -> Improve technical error recovery + retry | C19: =ICE_Backlog!C8 -> Website technical error | D19: =IFERROR(INDEX(ICE_Backlog!$G$4:$G$9,MATCH(A19,ICE_Backlog!$A$4:$A$9,0)),0) -> 0.245 | E19: =IFERROR(INDEX(ICE_Backlog!$J$4:$J$9,MATCH(A19,ICE_Backlog!$A$4:$A$9,0)),0) -> 359.51219 | F19: ICE_Backlog
A20: =ICE_Backlog!A9 -> FIX-06 | B20: =ICE_Backlog!B9 -> Add save-for-later / wishlist prompt | C20: =ICE_Backlog!C9 -> Just browsing/saved for later | D20: =IFERROR(INDEX(ICE_Backlog!$G$4:$G$9,MATCH(A20,ICE_Backlog!$A$4:$A$9,0)),0) -> 0.16 | E20: =IFERROR(INDEX(ICE_Backlog!$J$4:$J$9,MATCH(A20,ICE_Backlog!$A$4:$A$9,0)),0) -> 251.00488 | F20: ICE_Backlog

Sheet QA_Checks
A1: Epic 5 — Model QA Checks
A3: Check | B3: Result | C3: Expected | D3: Interpretation
A4: Abandonment count ties to generated source logic | B4: =Abandonment!C10 -> 322 | C4: 322 | D4: Cart + Checkout exits from 1,800 sessions
A5: Abandonment reason counts sum to total | B5: =SUM(Abandonment!I4:I9) -> 322 | C5: =Abandonment!C10 -> 322 | D5: Generated reason rows reconcile to abandonment sessions
A6: Reason shares sum to 100% | B6: =SUM(Abandonment!B4:B9) -> 1 | C6: 1 | D6: Weighted draw probabilities reconcile
A7: Revenue-share percentages sum to 100% | B7: =SUM(Abandonment!G4:G9) -> 1 | C7: 1 | D7: Revenue proxy allocation reconciles
A8: ICE backlog has 6 fixes | B8: =COUNTA(ICE_Backlog!A4:A9) -> 6 | C8: 6 | D8: Six proposed fixes
A9: ICE ranks cover 1–6 | B9: =COUNTIF(ICE_Backlog!H4:H9,1)+COUNTIF(ICE_Backlog!H4:H9,2)+COUNTIF(ICE_Backlog!H4:H9,3)+COUNTIF(ICE_Backlog!H4:H9,4)+COUNTIF(ICE_Backlog!H4:H9,5)+COUNTIF(ICE_Backlog!H4:H9,6) -> 6 | C9: 6 | D9: Every fix receives a rank
A10: What-if selector is populated | B10: =IF(What_If!B9<>"",1,0) -> 1 | C10: 1 | D10: Scenario selector has a valid value
A11: What-if selected AOV is numeric | B11: =ISNUMBER(What_If!D4) -> TRUE | C11: =TRUE() -> TRUE | D11: Lookup returns a numeric AOV
A12: What-if selected lift is numeric | B12: =ISNUMBER(What_If!E4) -> TRUE | C12: =TRUE() -> TRUE | D12: Lookup returns a numeric conversion lift
A14: Compatibility note | B14: INDEX/MATCH is used instead of XLOOKUP in the live lookup formulas so the workbook is less dependent on newer Excel function support.
